{
  "Tournament": {
    "Date": "2025-08-27",
    "Name": "Pioneer League",
    "Uri": "https://www.mtgo.com/decklist/pioneer-league-2025-08-279543",
    "Formats": "Pioneer"
  },
  "Decks": [
    {
      "Date": "2025-08-27T00:00:00+00:00",
      "Player": "Feitosa_",
      "Result": "5-0",
      "AnchorUri": "https://www.mtgo.com/decklist/pioneer-league-2025-08-279543#deck_Feitosa_",
      "Mainboard": [
        {
          "Count": 4,
          "CardName": "Adarkar Wastes"
        },
        {
          "Count": 1,
          "CardName": "Eiganjo, Seat of the Empire"
        },
        {
          "Count": 2,
          "CardName": "Enduring Curiosity"
        },
        {
          "Count": 4,
          "CardName": "Hallowed Fountain"
        },
        {
          "Count": 4,
          "CardName": "Hengegate Pathway"
        },
        {
          "Count": 1,
          "CardName": "Island"
        },
        {
          "Count": 1,
          "CardName": "Malcolm, Alluring Scoundrel"
        },
        {
          "Count": 4,
          "CardName": "Mausoleum Wanderer"
        },
        {
          "Count": 3,
          "CardName": "Mutavault"
        },
        {
          "Count": 4,
          "CardName": "No More Lies"
        },
        {
          "Count": 1,
          "CardName": "Otawara, Soaring City"
        },
        {
          "Count": 2,
          "CardName": "Plains"
        },
        {
          "Count": 4,
          "CardName": "Rattlechains"
        },
        {
          "Count": 4,
          "CardName": "Seachrome Coast"
        },
        {
          "Count": 3,
          "CardName": "Seam Rip"
        },
        {
          "Count": 3,
          "CardName": "Sheltered by Ghosts"
        },
        {
          "Count": 4,
          "CardName": "Skyclave Apparition"
        },
        {
          "Count": 1,
          "CardName": "Spell Pierce"
        },
        {
          "Count": 4,
          "CardName": "Spell Queller"
        },
        {
          "Count": 4,
          "CardName": "Supreme Phantom"
        },
        {
          "Count": 2,
          "CardName": "The Wandering Emperor"
        }
      ],
      "Sideboard": [
        {
          "Count": 1,
          "CardName": "Declaration in Stone"
        },
        {
          "Count": 1,
          "CardName": "Get Lost"
        },
        {
          "Count": 1,
          "CardName": "Invasion of Gobakhan"
        },
        {
          "Count": 2,
          "CardName": "Rest in Peace"
        },
        {
          "Count": 1,
          "CardName": "Seam Rip"
        },
        {
          "Count": 1,
          "CardName": "Spell Pierce"
        },
        {
          "Count": 1,
          "CardName": "Split Up"
        },
        {
          "Count": 2,
          "CardName": "Tishana's Tidebinder"
        },
        {
          "Count": 1,
          "CardName": "Tocasia's Welcome"
        },
        {
          "Count": 4,
          "CardName": "Wedding Announcement"
        }
      ]
    },
    {
      "Date": "2025-08-27T00:00:00+00:00",
      "Player": "sMann2.0",
      "Result": "5-0",
      "AnchorUri": "https://www.mtgo.com/decklist/pioneer-league-2025-08-279543#deck_sMann2.0",
      "Mainboard": [
        {
          "Count": 1,
          "CardName": "Atraxa, Grand Unifier"
        },
        {
          "Count": 4,
          "CardName": "Censor"
        },
        {
          "Count": 4,
          "CardName": "Deduce"
        },
        {
          "Count": 4,
          "CardName": "Fable of the Mirror-Breaker"
        },
        {
          "Count": 4,
          "CardName": "Indomitable Creativity"
        },
        {
          "Count": 3,
          "CardName": "Mirrex"
        },
        {
          "Count": 3,
          "CardName": "Mountain"
        },
        {
          "Count": 1,
          "CardName": "Narset, Parter of Veils"
        },
        {
          "Count": 4,
          "CardName": "Prismari Command"
        },
        {
          "Count": 4,
          "CardName": "Riverglide Pathway"
        },
        {
          "Count": 1,
          "CardName": "Riverpyre Verge"
        },
        {
          "Count": 1,
          "CardName": "Shark Typhoon"
        },
        {
          "Count": 2,
          "CardName": "Shivan Reef"
        },
        {
          "Count": 1,
          "CardName": "Sokenzan, Crucible of Defiance"
        },
        {
          "Count": 4,
          "CardName": "Spell Pierce"
        },
        {
          "Count": 4,
          "CardName": "Spirebluff Canal"
        },
        {
          "Count": 4,
          "CardName": "Steam Vents"
        },
        {
          "Count": 2,
          "CardName": "Temple of Epiphany"
        },
        {
          "Count": 2,
          "CardName": "Torch the Tower"
        },
        {
          "Count": 2,
          "CardName": "Unable to Scream"
        },
        {
          "Count": 1,
          "CardName": "Valgavoth, Terror Eater"
        },
        {
          "Count": 4,
          "CardName": "Volcanic Spite"
        }
      ],
      "Sideboard": [
        {
          "Count": 4,
          "CardName": "Aether Gust"
        },
        {
          "Count": 4,
          "CardName": "Leyline of Sanctity"
        },
        {
          "Count": 3,
          "CardName": "Narset, Parter of Veils"
        },
        {
          "Count": 1,
          "CardName": "Portal to Phyrexia"
        },
        {
          "Count": 3,
          "CardName": "Shark Typhoon"
        }
      ]
    },
    {
      "Date": "2025-08-27T00:00:00+00:00",
      "Player": "RNAPBP1",
      "Result": "5-0",
      "AnchorUri": "https://www.mtgo.com/decklist/pioneer-league-2025-08-279543#deck_RNAPBP1",
      "Mainboard": [
        {
          "Count": 2,
          "CardName": "Consult the Star Charts"
        },
        {
          "Count": 13,
          "CardName": "Island"
        },
        {
          "Count": 2,
          "CardName": "Kitsa, Otterball Elite"
        },
        {
          "Count": 1,
          "CardName": "Magic Damper"
        },
        {
          "Count": 3,
          "CardName": "Mox Amber"
        },
        {
          "Count": 3,
          "CardName": "Mox Jasper"
        },
        {
          "Count": 4,
          "CardName": "Mutavault"
        },
        {
          "Count": 1,
          "CardName": "Otawara, Soaring City"
        },
        {
          "Count": 1,
          "CardName": "Proft's Eidetic Memory"
        },
        {
          "Count": 4,
          "CardName": "Retraction Helix"
        },
        {
          "Count": 4,
          "CardName": "Rona, Herald of Invasion"
        },
        {
          "Count": 3,
          "CardName": "Sea Gate Restoration"
        },
        {
          "Count": 1,
          "CardName": "Shore Up"
        },
        {
          "Count": 4,
          "CardName": "Sleight of Hand"
        },
        {
          "Count": 1,
          "CardName": "Soulstone Sanctuary"
        },
        {
          "Count": 4,
          "CardName": "Stock Up"
        },
        {
          "Count": 3,
          "CardName": "Stormchaser's Talent"
        },
        {
          "Count": 2,
          "CardName": "Thundertrap Trainer"
        },
        {
          "Count": 4,
          "CardName": "Valley Floodcaller"
        }
      ],
      "Sideboard": [
        {
          "Count": 4,
          "CardName": "Annul"
        },
        {
          "Count": 2,
          "CardName": "Caelorna, Coral Tyrant"
        },
        {
          "Count": 1,
          "CardName": "Dispel"
        },
        {
          "Count": 2,
          "CardName": "Ghost Vacuum"
        },
        {
          "Count": 3,
          "CardName": "Into the Flood Maw"
        },
        {
          "Count": 2,
          "CardName": "Shore Up"
        },
        {
          "Count": 1,
          "CardName": "Spell Pierce"
        }
      ]
    }
  ],
  "Rounds": [],
  "Standings": []
}