{
  "Tournament": {
    "Date": "2025-12-23T23:00:00+00:00",
    "Name": "Monthly PM Olympus Garden Diciembre",
    "Uri": "https://melee.gg/Tournament/View/389825",
    "Formats": "Premodern"
  },
  "Decks": [
    {
      "Date": null,
      "Player": "Oscar Zamora",
      "Result": "1st Place",
      "AnchorUri": "https://melee.gg/Decklist/View/17f446a3-e19e-4dec-ad2a-b3bc01289cdf",
      "Mainboard": [
        {
          "Count": 4,
          "CardName": "Counterspell"
        },
        {
          "Count": 1,
          "CardName": "Coastal Tower"
        },
        {
          "Count": 6,
          "CardName": "Island"
        },
        {
          "Count": 1,
          "CardName": "Powder Keg"
        },
        {
          "Count": 4,
          "CardName": "Flooded Strand"
        },
        {
          "Count": 2,
          "CardName": "Seal of Cleansing"
        },
        {
          "Count": 3,
          "CardName": "Impulse"
        },
        {
          "Count": 4,
          "CardName": "Swords to Plowshares"
        },
        {
          "Count": 4,
          "CardName": "Mishra's Factory"
        },
        {
          "Count": 4,
          "CardName": "Adarkar Wastes"
        },
        {
          "Count": 2,
          "CardName": "Faerie Conclave"
        },
        {
          "Count": 1,
          "CardName": "Humility"
        },
        {
          "Count": 3,
          "CardName": "Parallax Tide"
        },
        {
          "Count": 2,
          "CardName": "Dust Bowl"
        },
        {
          "Count": 3,
          "CardName": "Standstill"
        },
        {
          "Count": 2,
          "CardName": "Chain of Vapor"
        },
        {
          "Count": 3,
          "CardName": "Mana Leak"
        },
        {
          "Count": 3,
          "CardName": "Plains"
        },
        {
          "Count": 3,
          "CardName": "Fact or Fiction"
        },
        {
          "Count": 1,
          "CardName": "Stifle"
        },
        {
          "Count": 2,
          "CardName": "Wrath of God"
        },
        {
          "Count": 2,
          "CardName": "Decree of Justice"
        }
      ],
      "Sideboard": [
        {
          "Count": 1,
          "CardName": "Aura of Silence"
        },
        {
          "Count": 1,
          "CardName": "Circle of Protection: Red"
        },
        {
          "Count": 3,
          "CardName": "Hydroblast"
        },
        {
          "Count": 1,
          "CardName": "Cursed Totem"
        },
        {
          "Count": 1,
          "CardName": "Blue Elemental Blast"
        },
        {
          "Count": 1,
          "CardName": "Teferi's Response"
        },
        {
          "Count": 2,
          "CardName": "Meddling Mage"
        },
        {
          "Count": 3,
          "CardName": "Annul"
        },
        {
          "Count": 1,
          "CardName": "Tormod's Crypt"
        },
        {
          "Count": 1,
          "CardName": "Hibernation"
        }
      ]
    },
    {
      "Date": null,
      "Player": "Ricardo Abarca",
      "Result": "2st Place",
      "AnchorUri": "https://melee.gg/Decklist/View/f50c28aa-e826-42a3-922c-b3bc015d5614",
      "Mainboard": [
        {
          "Count": 4,
          "CardName": "Counterspell"
        },
        {
          "Count": 3,
          "CardName": "Swamp"
        },
        {
          "Count": 2,
          "CardName": "Forest"
        },
        {
          "Count": 2,
          "CardName": "Grizzly Fate"
        },
        {
          "Count": 3,
          "CardName": "City of Brass"
        },
        {
          "Count": 2,
          "CardName": "Gaea's Blessing"
        },
        {
          "Count": 2,
          "CardName": "Reflecting Pool"
        },
        {
          "Count": 4,
          "CardName": "Accumulated Knowledge"
        },
        {
          "Count": 4,
          "CardName": "Duress"
        },
        {
          "Count": 3,
          "CardName": "Island"
        },
        {
          "Count": 2,
          "CardName": "Llanowar Wastes"
        },
        {
          "Count": 2,
          "CardName": "Diabolic Edict"
        },
        {
          "Count": 1,
          "CardName": "Lat-Nam's Legacy"
        },
        {
          "Count": 1,
          "CardName": "Mystic Snake"
        },
        {
          "Count": 2,
          "CardName": "Underground River"
        },
        {
          "Count": 3,
          "CardName": "Yavimaya Coast"
        },
        {
          "Count": 1,
          "CardName": "Ravenous Baloth"
        },
        {
          "Count": 4,
          "CardName": "Polluted Delta"
        },
        {
          "Count": 1,
          "CardName": "Annul"
        },
        {
          "Count": 1,
          "CardName": "Mana Leak"
        },
        {
          "Count": 2,
          "CardName": "Smother"
        },
        {
          "Count": 3,
          "CardName": "Fact or Fiction"
        },
        {
          "Count": 4,
          "CardName": "Wall of Blossoms"
        },
        {
          "Count": 4,
          "CardName": "Pernicious Deed"
        }
      ],
      "Sideboard": [
        {
          "Count": 2,
          "CardName": "Chill"
        },
        {
          "Count": 2,
          "CardName": "Naturalize"
        },
        {
          "Count": 3,
          "CardName": "Call of the Herd"
        },
        {
          "Count": 1,
          "CardName": "Phantom Nishoba"
        },
        {
          "Count": 3,
          "CardName": "Oath of Druids"
        },
        {
          "Count": 1,
          "CardName": "Akroma, Angel of Wrath"
        },
        {
          "Count": 2,
          "CardName": "Annul"
        },
        {
          "Count": 1,
          "CardName": "Haunting Echoes"
        }
      ]
    },
    {
      "Date": null,
      "Player": "edkeytar",
      "Result": "3st Place",
      "AnchorUri": "https://melee.gg/Decklist/View/3a1501f4-2f15-4029-ae4f-b3bc01224347",
      "Mainboard": [
        {
          "Count": 4,
          "CardName": "Dark Ritual"
        },
        {
          "Count": 4,
          "CardName": "Lord of the Undead"
        },
        {
          "Count": 4,
          "CardName": "Twisted Abomination"
        },
        {
          "Count": 4,
          "CardName": "Withered Wretch"
        },
        {
          "Count": 2,
          "CardName": "Graveborn Muse"
        },
        {
          "Count": 1,
          "CardName": "Cabal Coffers"
        },
        {
          "Count": 4,
          "CardName": "Cabal Therapy"
        },
        {
          "Count": 4,
          "CardName": "Gempalm Polluter"
        },
        {
          "Count": 1,
          "CardName": "Tombstone Stairwell"
        },
        {
          "Count": 4,
          "CardName": "Carnophage"
        },
        {
          "Count": 4,
          "CardName": "Carrion Feeder"
        },
        {
          "Count": 15,
          "CardName": "Swamp"
        },
        {
          "Count": 3,
          "CardName": "Living Death"
        },
        {
          "Count": 2,
          "CardName": "Undead Gladiator"
        },
        {
          "Count": 4,
          "CardName": "Wasteland"
        }
      ],
      "Sideboard": [
        {
          "Count": 4,
          "CardName": "Engineered Plague"
        },
        {
          "Count": 3,
          "CardName": "Smother"
        },
        {
          "Count": 1,
          "CardName": "Tormod's Crypt"
        },
        {
          "Count": 2,
          "CardName": "Gloom"
        },
        {
          "Count": 4,
          "CardName": "Duress"
        },
        {
          "Count": 1,
          "CardName": "Haunting Echoes"
        }
      ]
    },
    {
      "Date": null,
      "Player": "CentralLiving",
      "Result": "4th Place",
      "AnchorUri": "https://melee.gg/Decklist/View/23e676e1-1f35-4174-9a2d-b3bc0162c04f",
      "Mainboard": [
        {
          "Count": 4,
          "CardName": "Call of the Herd"
        },
        {
          "Count": 4,
          "CardName": "Windswept Heath"
        },
        {
          "Count": 3,
          "CardName": "Forest"
        },
        {
          "Count": 3,
          "CardName": "Undiscovered Paradise"
        },
        {
          "Count": 1,
          "CardName": "Glory"
        },
        {
          "Count": 1,
          "CardName": "Deep Analysis"
        },
        {
          "Count": 4,
          "CardName": "Tireless Tribe"
        },
        {
          "Count": 4,
          "CardName": "Swords to Plowshares"
        },
        {
          "Count": 1,
          "CardName": "Ray of Revelation"
        },
        {
          "Count": 4,
          "CardName": "City of Brass"
        },
        {
          "Count": 1,
          "CardName": "Treva's Ruins"
        },
        {
          "Count": 3,
          "CardName": "Quiet Speculation"
        },
        {
          "Count": 4,
          "CardName": "About Face"
        },
        {
          "Count": 1,
          "CardName": "Prismatic Strands"
        },
        {
          "Count": 1,
          "CardName": "Roar of the Wurm"
        },
        {
          "Count": 1,
          "CardName": "Volcanic Spray"
        },
        {
          "Count": 4,
          "CardName": "Circular Logic"
        },
        {
          "Count": 3,
          "CardName": "Mother of Runes"
        },
        {
          "Count": 2,
          "CardName": "Plains"
        },
        {
          "Count": 4,
          "CardName": "Gemstone Mine"
        },
        {
          "Count": 3,
          "CardName": "Arrogant Wurm"
        },
        {
          "Count": 4,
          "CardName": "Wild Mongrel"
        }
      ],
      "Sideboard": [
        {
          "Count": 1,
          "CardName": "Aura of Silence"
        },
        {
          "Count": 1,
          "CardName": "Circle of Protection: Red"
        },
        {
          "Count": 1,
          "CardName": "Ray of Revelation"
        },
        {
          "Count": 1,
          "CardName": "Phyrexian Furnace"
        },
        {
          "Count": 1,
          "CardName": "Warmth"
        },
        {
          "Count": 2,
          "CardName": "Engineered Plague"
        },
        {
          "Count": 2,
          "CardName": "Armageddon"
        },
        {
          "Count": 1,
          "CardName": "Tormod's Crypt"
        },
        {
          "Count": 2,
          "CardName": "Disenchant"
        },
        {
          "Count": 1,
          "CardName": "Enlightened Tutor"
        },
        {
          "Count": 1,
          "CardName": "Naturalize"
        },
        {
          "Count": 1,
          "CardName": "Rune of Protection: Artifacts"
        }
      ]
    },
    {
      "Date": null,
      "Player": "DavidAraya",
      "Result": "5th Place",
      "AnchorUri": "https://melee.gg/Decklist/View/1acfc87b-3e9d-48a3-ac73-b3bc015dca89",
      "Mainboard": [
        {
          "Count": 1,
          "CardName": "Cunning Wish"
        },
        {
          "Count": 4,
          "CardName": "Merchant Scroll"
        },
        {
          "Count": 3,
          "CardName": "Arcane Denial"
        },
        {
          "Count": 18,
          "CardName": "Island"
        },
        {
          "Count": 4,
          "CardName": "Lotus Petal"
        },
        {
          "Count": 4,
          "CardName": "Sapphire Medallion"
        },
        {
          "Count": 3,
          "CardName": "Brain Freeze"
        },
        {
          "Count": 4,
          "CardName": "Helm of Awakening"
        },
        {
          "Count": 4,
          "CardName": "Meditate"
        },
        {
          "Count": 3,
          "CardName": "Words of Wisdom"
        },
        {
          "Count": 1,
          "CardName": "Chain of Vapor"
        },
        {
          "Count": 1,
          "CardName": "Fact or Fiction"
        },
        {
          "Count": 1,
          "CardName": "Turnabout"
        },
        {
          "Count": 4,
          "CardName": "Sleight of Hand"
        },
        {
          "Count": 4,
          "CardName": "Frantic Search"
        },
        {
          "Count": 1,
          "CardName": "Recall"
        }
      ],
      "Sideboard": [
        {
          "Count": 1,
          "CardName": "Arcane Denial"
        },
        {
          "Count": 1,
          "CardName": "Brain Freeze"
        },
        {
          "Count": 3,
          "CardName": "Defense Grid"
        },
        {
          "Count": 1,
          "CardName": "Mana Short"
        },
        {
          "Count": 2,
          "CardName": "Annul"
        },
        {
          "Count": 2,
          "CardName": "Tormod's Crypt"
        },
        {
          "Count": 1,
          "CardName": "Chain of Vapor"
        },
        {
          "Count": 2,
          "CardName": "Propaganda"
        },
        {
          "Count": 1,
          "CardName": "Hibernation"
        },
        {
          "Count": 1,
          "CardName": "Misdirection"
        }
      ]
    },
    {
      "Date": null,
      "Player": "Zenzaz",
      "Result": "6th Place",
      "AnchorUri": "https://melee.gg/Decklist/View/25e1b0da-dac3-47ef-9168-b3bb00518f02",
      "Mainboard": [
        {
          "Count": 2,
          "CardName": "Sutured Ghoul"
        },
        {
          "Count": 1,
          "CardName": "Genesis"
        },
        {
          "Count": 1,
          "CardName": "Nantuko Vigilante"
        },
        {
          "Count": 4,
          "CardName": "Survival of the Fittest"
        },
        {
          "Count": 1,
          "CardName": "Apprentice Necromancer"
        },
        {
          "Count": 3,
          "CardName": "Cabal Therapy"
        },
        {
          "Count": 1,
          "CardName": "Mesmeric Fiend"
        },
        {
          "Count": 3,
          "CardName": "City of Brass"
        },
        {
          "Count": 5,
          "CardName": "Forest"
        },
        {
          "Count": 1,
          "CardName": "Deranged Hermit"
        },
        {
          "Count": 1,
          "CardName": "Sylvan Safekeeper"
        },
        {
          "Count": 4,
          "CardName": "Birds of Paradise"
        },
        {
          "Count": 3,
          "CardName": "Duress"
        },
        {
          "Count": 1,
          "CardName": "Squee, Goblin Nabob"
        },
        {
          "Count": 5,
          "CardName": "Swamp"
        },
        {
          "Count": 4,
          "CardName": "Llanowar Wastes"
        },
        {
          "Count": 1,
          "CardName": "Corpse Dance"
        },
        {
          "Count": 4,
          "CardName": "Dark Ritual"
        },
        {
          "Count": 1,
          "CardName": "Bone Shredder"
        },
        {
          "Count": 4,
          "CardName": "Krosan Cloudscraper"
        },
        {
          "Count": 1,
          "CardName": "Wall of Roots"
        },
        {
          "Count": 1,
          "CardName": "Sylvan Library"
        },
        {
          "Count": 4,
          "CardName": "Shallow Grave"
        },
        {
          "Count": 4,
          "CardName": "Buried Alive"
        }
      ],
      "Sideboard": [
        {
          "Count": 2,
          "CardName": "Powder Keg"
        },
        {
          "Count": 3,
          "CardName": "Naturalize"
        },
        {
          "Count": 1,
          "CardName": "Sylvan Safekeeper"
        },
        {
          "Count": 1,
          "CardName": "Crumble"
        },
        {
          "Count": 1,
          "CardName": "Spike Feeder"
        },
        {
          "Count": 3,
          "CardName": "Engineered Plague"
        },
        {
          "Count": 1,
          "CardName": "Withered Wretch"
        },
        {
          "Count": 2,
          "CardName": "Smother"
        },
        {
          "Count": 1,
          "CardName": "Uktabi Orangutan"
        }
      ]
    },
    {
      "Date": null,
      "Player": "Ale Focardi",
      "Result": "7th Place",
      "AnchorUri": "https://melee.gg/Decklist/View/a0c4347d-0c56-4711-807f-b3bc015ee9a8",
      "Mainboard": [
        {
          "Count": 1,
          "CardName": "Swamp"
        },
        {
          "Count": 2,
          "CardName": "Svyelunite Temple"
        },
        {
          "Count": 1,
          "CardName": "Deep Analysis"
        },
        {
          "Count": 2,
          "CardName": "City of Traitors"
        },
        {
          "Count": 4,
          "CardName": "Lim-Dûl's Vault"
        },
        {
          "Count": 2,
          "CardName": "Illusions of Grandeur"
        },
        {
          "Count": 1,
          "CardName": "Brain Freeze"
        },
        {
          "Count": 3,
          "CardName": "Impulse"
        },
        {
          "Count": 4,
          "CardName": "Dream Halls"
        },
        {
          "Count": 4,
          "CardName": "Lotus Petal"
        },
        {
          "Count": 3,
          "CardName": "Island"
        },
        {
          "Count": 3,
          "CardName": "Rush of Knowledge"
        },
        {
          "Count": 3,
          "CardName": "Ancient Tomb"
        },
        {
          "Count": 4,
          "CardName": "Underground River"
        },
        {
          "Count": 1,
          "CardName": "Flash of Insight"
        },
        {
          "Count": 3,
          "CardName": "Donate"
        },
        {
          "Count": 4,
          "CardName": "Opportunity"
        },
        {
          "Count": 4,
          "CardName": "Meditate"
        },
        {
          "Count": 4,
          "CardName": "Polluted Delta"
        },
        {
          "Count": 1,
          "CardName": "Chain of Vapor"
        },
        {
          "Count": 3,
          "CardName": "Show and Tell"
        },
        {
          "Count": 1,
          "CardName": "Forbidden Crypt"
        },
        {
          "Count": 2,
          "CardName": "Frantic Search"
        }
      ],
      "Sideboard": [
        {
          "Count": 1,
          "CardName": "Hypnox"
        },
        {
          "Count": 2,
          "CardName": "Arcane Denial"
        },
        {
          "Count": 1,
          "CardName": "Lobotomy"
        },
        {
          "Count": 2,
          "CardName": "Phyrexian Negator"
        },
        {
          "Count": 3,
          "CardName": "Defense Grid"
        },
        {
          "Count": 1,
          "CardName": "Teferi's Response"
        },
        {
          "Count": 1,
          "CardName": "Mana Short"
        },
        {
          "Count": 2,
          "CardName": "Tormod's Crypt"
        },
        {
          "Count": 2,
          "CardName": "Propaganda"
        }
      ]
    },
    {
      "Date": null,
      "Player": "JuanMaGabriel",
      "Result": "8th Place",
      "AnchorUri": "https://melee.gg/Decklist/View/e846d620-1472-4152-9291-b3bc0005fae0",
      "Mainboard": [
        {
          "Count": 2,
          "CardName": "Phantom Nishoba"
        },
        {
          "Count": 3,
          "CardName": "Swamp"
        },
        {
          "Count": 4,
          "CardName": "Living Wish"
        },
        {
          "Count": 3,
          "CardName": "Forest"
        },
        {
          "Count": 4,
          "CardName": "Windswept Heath"
        },
        {
          "Count": 1,
          "CardName": "Seal of Cleansing"
        },
        {
          "Count": 4,
          "CardName": "Swords to Plowshares"
        },
        {
          "Count": 1,
          "CardName": "Akroma, Angel of Wrath"
        },
        {
          "Count": 4,
          "CardName": "Oath of Druids"
        },
        {
          "Count": 2,
          "CardName": "City of Brass"
        },
        {
          "Count": 3,
          "CardName": "Treetop Village"
        },
        {
          "Count": 2,
          "CardName": "Gaea's Blessing"
        },
        {
          "Count": 4,
          "CardName": "Vindicate"
        },
        {
          "Count": 4,
          "CardName": "Duress"
        },
        {
          "Count": 3,
          "CardName": "Caves of Koilos"
        },
        {
          "Count": 4,
          "CardName": "Llanowar Wastes"
        },
        {
          "Count": 2,
          "CardName": "Gerrard's Verdict"
        },
        {
          "Count": 2,
          "CardName": "Funeral Pyre"
        },
        {
          "Count": 3,
          "CardName": "Plains"
        },
        {
          "Count": 1,
          "CardName": "Enlightened Tutor"
        },
        {
          "Count": 4,
          "CardName": "Pernicious Deed"
        }
      ],
      "Sideboard": [
        {
          "Count": 1,
          "CardName": "Sacred Ground"
        },
        {
          "Count": 1,
          "CardName": "Circle of Protection: Red"
        },
        {
          "Count": 1,
          "CardName": "Seal of Cleansing"
        },
        {
          "Count": 1,
          "CardName": "Monk Realist"
        },
        {
          "Count": 1,
          "CardName": "Ray of Revelation"
        },
        {
          "Count": 1,
          "CardName": "Mystic Enforcer"
        },
        {
          "Count": 1,
          "CardName": "Exalted Angel"
        },
        {
          "Count": 1,
          "CardName": "Engineered Plague"
        },
        {
          "Count": 1,
          "CardName": "Kor Haven"
        },
        {
          "Count": 1,
          "CardName": "Dust Bowl"
        },
        {
          "Count": 1,
          "CardName": "Withered Wretch"
        },
        {
          "Count": 1,
          "CardName": "Ravenous Baloth"
        },
        {
          "Count": 1,
          "CardName": "Naturalize"
        },
        {
          "Count": 1,
          "CardName": "Plague Spitter"
        },
        {
          "Count": 1,
          "CardName": "Uktabi Orangutan"
        }
      ]
    },
    {
      "Date": null,
      "Player": "Esteban Gonzalez",
      "Result": "9th Place",
      "AnchorUri": "https://melee.gg/Decklist/View/f91ed933-1b72-41bc-8ae0-b3bb0054b654",
      "Mainboard": [
        {
          "Count": 4,
          "CardName": "Dark Ritual"
        },
        {
          "Count": 3,
          "CardName": "Phyrexian Arena"
        },
        {
          "Count": 1,
          "CardName": "Dust Bowl"
        },
        {
          "Count": 2,
          "CardName": "Withered Wretch"
        },
        {
          "Count": 4,
          "CardName": "Gerrard's Verdict"
        },
        {
          "Count": 3,
          "CardName": "Plains"
        },
        {
          "Count": 4,
          "CardName": "Swords to Plowshares"
        },
        {
          "Count": 1,
          "CardName": "Disenchant"
        },
        {
          "Count": 3,
          "CardName": "Tainted Field"
        },
        {
          "Count": 4,
          "CardName": "Vindicate"
        },
        {
          "Count": 4,
          "CardName": "Exalted Angel"
        },
        {
          "Count": 4,
          "CardName": "Duress"
        },
        {
          "Count": 11,
          "CardName": "Swamp"
        },
        {
          "Count": 4,
          "CardName": "Nantuko Shade"
        },
        {
          "Count": 4,
          "CardName": "Caves of Koilos"
        },
        {
          "Count": 4,
          "CardName": "Hypnotic Specter"
        }
      ],
      "Sideboard": [
        {
          "Count": 3,
          "CardName": "Engineered Plague"
        },
        {
          "Count": 2,
          "CardName": "Circle of Protection: Red"
        },
        {
          "Count": 2,
          "CardName": "Smother"
        },
        {
          "Count": 2,
          "CardName": "Tormod's Crypt"
        },
        {
          "Count": 2,
          "CardName": "Disenchant"
        },
        {
          "Count": 2,
          "CardName": "Perish"
        },
        {
          "Count": 2,
          "CardName": "Black Knight"
        }
      ]
    },
    {
      "Date": null,
      "Player": "dmeza",
      "Result": "10th Place",
      "AnchorUri": "https://melee.gg/Decklist/View/fc508f4e-e962-45d6-9899-b3bc015ed0ba",
      "Mainboard": [
        {
          "Count": 4,
          "CardName": "Reanimate"
        },
        {
          "Count": 4,
          "CardName": "Hermit Druid"
        },
        {
          "Count": 1,
          "CardName": "Sutured Ghoul"
        },
        {
          "Count": 3,
          "CardName": "Vision Charm"
        },
        {
          "Count": 1,
          "CardName": "Reflecting Pool"
        },
        {
          "Count": 4,
          "CardName": "City of Brass"
        },
        {
          "Count": 4,
          "CardName": "Lotus Petal"
        },
        {
          "Count": 1,
          "CardName": "Sylvan Safekeeper"
        },
        {
          "Count": 4,
          "CardName": "Duress"
        },
        {
          "Count": 4,
          "CardName": "Llanowar Wastes"
        },
        {
          "Count": 1,
          "CardName": "Dragon Breath"
        },
        {
          "Count": 4,
          "CardName": "Yavimaya Coast"
        },
        {
          "Count": 4,
          "CardName": "Underground River"
        },
        {
          "Count": 1,
          "CardName": "Cabal Therapy"
        },
        {
          "Count": 4,
          "CardName": "Stifle"
        },
        {
          "Count": 1,
          "CardName": "Elvish Spirit Guide"
        },
        {
          "Count": 4,
          "CardName": "Gemstone Mine"
        },
        {
          "Count": 4,
          "CardName": "Worldly Tutor"
        },
        {
          "Count": 4,
          "CardName": "Phyrexian Dreadnought"
        },
        {
          "Count": 1,
          "CardName": "Krosan Reclamation"
        },
        {
          "Count": 2,
          "CardName": "Shallow Grave"
        }
      ],
      "Sideboard": [
        {
          "Count": 1,
          "CardName": "Sutured Ghoul"
        },
        {
          "Count": 2,
          "CardName": "Ray of Revelation"
        },
        {
          "Count": 2,
          "CardName": "Sylvan Safekeeper"
        },
        {
          "Count": 3,
          "CardName": "Orim's Chant"
        },
        {
          "Count": 1,
          "CardName": "Krosan Reclamation"
        },
        {
          "Count": 1,
          "CardName": "Cabal Therapy"
        },
        {
          "Count": 1,
          "CardName": "Chain of Vapor"
        },
        {
          "Count": 1,
          "CardName": "Flaring Pain"
        },
        {
          "Count": 2,
          "CardName": "Shallow Grave"
        },
        {
          "Count": 1,
          "CardName": "Uktabi Orangutan"
        }
      ]
    }
  ],
  "Rounds": [
    {
      "RoundName": "Round 1",
      "Matches": [
        {
          "Player1": "Oscar Zamora",
          "Player2": "Zenzaz",
          "Result": "2-1-0"
        },
        {
          "Player1": "Ricardo Abarca",
          "Player2": "DavidAraya",
          "Result": "2-0-0"
        },
        {
          "Player1": "edkeytar",
          "Player2": "Esteban Gonzalez",
          "Result": "2-1-0"
        },
        {
          "Player1": "CentralLiving",
          "Player2": "JuanMaGabriel",
          "Result": "2-0-0"
        },
        {
          "Player1": "Ale Focardi",
          "Player2": "dmeza",
          "Result": "2-1-0"
        }
      ]
    },
    {
      "RoundName": "Round 2",
      "Matches": [
        {
          "Player1": "Oscar Zamora",
          "Player2": "Ale Focardi",
          "Result": "2-0-0"
        },
        {
          "Player1": "Ricardo Abarca",
          "Player2": "edkeytar",
          "Result": "2-1-0"
        },
        {
          "Player1": "CentralLiving",
          "Player2": "Zenzaz",
          "Result": "2-1-0"
        },
        {
          "Player1": "DavidAraya",
          "Player2": "Esteban Gonzalez",
          "Result": "2-1-0"
        },
        {
          "Player1": "JuanMaGabriel",
          "Player2": "dmeza",
          "Result": "2-0-0"
        }
      ]
    },
    {
      "RoundName": "Round 3",
      "Matches": [
        {
          "Player1": "Oscar Zamora",
          "Player2": "DavidAraya",
          "Result": "2-1-0"
        },
        {
          "Player1": "Ricardo Abarca",
          "Player2": "CentralLiving",
          "Result": "2-0-0"
        },
        {
          "Player1": "edkeytar",
          "Player2": "JuanMaGabriel",
          "Result": "2-1-0"
        },
        {
          "Player1": "Zenzaz",
          "Player2": "dmeza",
          "Result": "2-1-0"
        },
        {
          "Player1": "Esteban Gonzalez",
          "Player2": "Ale Focardi",
          "Result": "2-1-0"
        }
      ]
    },
    {
      "RoundName": "Round 4",
      "Matches": [
        {
          "Player1": "Oscar Zamora",
          "Player2": "Ricardo Abarca",
          "Result": "2-1-0"
        },
        {
          "Player1": "edkeytar",
          "Player2": "CentralLiving",
          "Result": "0-0-3"
        },
        {
          "Player1": "CentralLiving",
          "Player2": "edkeytar",
          "Result": "0-0-3"
        },
        {
          "Player1": "DavidAraya",
          "Player2": "dmeza",
          "Result": "0-0-3"
        },
        {
          "Player1": "Zenzaz",
          "Player2": "Esteban Gonzalez",
          "Result": "0-0-3"
        },
        {
          "Player1": "Ale Focardi",
          "Player2": "JuanMaGabriel",
          "Result": "0-0-0"
        },
        {
          "Player1": "JuanMaGabriel",
          "Player2": "Ale Focardi",
          "Result": "0-0-0"
        },
        {
          "Player1": "Esteban Gonzalez",
          "Player2": "Zenzaz",
          "Result": "0-0-3"
        },
        {
          "Player1": "dmeza",
          "Player2": "DavidAraya",
          "Result": "0-0-3"
        }
      ]
    }
  ],
  "Standings": [
    {
      "Rank": 1,
      "Player": "Oscar Zamora",
      "Points": 12,
      "Wins": 4,
      "Losses": 0,
      "Draws": 0,
      "OMWP": 0.4375,
      "GWP": 0.7272727,
      "OGWP": 0.4638258
    },
    {
      "Rank": 2,
      "Player": "Ricardo Abarca",
      "Points": 9,
      "Wins": 3,
      "Losses": 1,
      "Draws": 0,
      "OMWP": 0.625,
      "GWP": 0.7,
      "OGWP": 0.5227273
    },
    {
      "Rank": 3,
      "Player": "edkeytar",
      "Points": 7,
      "Wins": 2,
      "Losses": 1,
      "Draws": 1,
      "OMWP": 0.5,
      "GWP": 0.5,
      "OGWP": 0.5113095
    },
    {
      "Rank": 4,
      "Player": "CentralLiving",
      "Points": 7,
      "Wins": 2,
      "Losses": 1,
      "Draws": 1,
      "OMWP": 0.5,
      "GWP": 0.5,
      "OGWP": 0.5113095
    },
    {
      "Rank": 5,
      "Player": "DavidAraya",
      "Points": 4,
      "Wins": 1,
      "Losses": 2,
      "Draws": 1,
      "OMWP": 0.6041667,
      "GWP": 0.3636364,
      "OGWP": 0.5443182
    },
    {
      "Rank": 6,
      "Player": "Zenzaz",
      "Points": 4,
      "Wins": 1,
      "Losses": 2,
      "Draws": 1,
      "OMWP": 0.5625,
      "GWP": 0.4166667,
      "OGWP": 0.4943182
    },
    {
      "Rank": 7,
      "Player": "Ale Focardi",
      "Points": 4,
      "Wins": 1,
      "Losses": 2,
      "Draws": 1,
      "OMWP": 0.5,
      "GWP": 0.375,
      "OGWP": 0.476461
    },
    {
      "Rank": 8,
      "Player": "JuanMaGabriel",
      "Points": 4,
      "Wins": 1,
      "Losses": 2,
      "Draws": 1,
      "OMWP": 0.4583333,
      "GWP": 0.4285714,
      "OGWP": 0.4270833
    },
    {
      "Rank": 9,
      "Player": "Esteban Gonzalez",
      "Points": 4,
      "Wins": 1,
      "Losses": 2,
      "Draws": 1,
      "OMWP": 0.3958333,
      "GWP": 0.4166667,
      "OGWP": 0.4138258
    },
    {
      "Rank": 10,
      "Player": "dmeza",
      "Points": 1,
      "Wins": 0,
      "Losses": 3,
      "Draws": 1,
      "OMWP": 0.3333333,
      "GWP": 0.3333333,
      "OGWP": 0.3959686
    }
  ]
}