{
  "Tournament": {
    "Date": "2025-06-27",
    "Name": "Standard League",
    "Uri": "https://www.mtgo.com/decklist/standard-league-2025-06-279382",
    "Formats": "Standard"
  },
  "Decks": [
    {
      "Date": "2025-06-27T00:00:00+00:00",
      "Player": "DskBayWolf",
      "Result": "5-0",
      "AnchorUri": "https://www.mtgo.com/decklist/standard-league-2025-06-279382#deck_DskBayWolf",
      "Mainboard": [
        {
          "Count": 4,
          "CardName": "Battlefield Forge"
        },
        {
          "Count": 4,
          "CardName": "Bruse Tarl, Roving Rancher"
        },
        {
          "Count": 4,
          "CardName": "Burst Lightning"
        },
        {
          "Count": 1,
          "CardName": "Cori Mountain Monastery"
        },
        {
          "Count": 1,
          "CardName": "Elspeth, Storm Slayer"
        },
        {
          "Count": 4,
          "CardName": "Inspiring Vantage"
        },
        {
          "Count": 1,
          "CardName": "Joshua, Phoenix's Dominant"
        },
        {
          "Count": 1,
          "CardName": "Lavaspur Boots"
        },
        {
          "Count": 4,
          "CardName": "Lightning Helix"
        },
        {
          "Count": 2,
          "CardName": "Lightning, Army of One"
        },
        {
          "Count": 4,
          "CardName": "Magebane Lizard"
        },
        {
          "Count": 4,
          "CardName": "Mountain"
        },
        {
          "Count": 3,
          "CardName": "Plains"
        },
        {
          "Count": 2,
          "CardName": "Restless Bivouac"
        },
        {
          "Count": 4,
          "CardName": "Screaming Nemesis"
        },
        {
          "Count": 4,
          "CardName": "Sheltered by Ghosts"
        },
        {
          "Count": 3,
          "CardName": "Soulstone Sanctuary"
        },
        {
          "Count": 2,
          "CardName": "Summon: Brynhildr"
        },
        {
          "Count": 4,
          "CardName": "Sunbillow Verge"
        },
        {
          "Count": 4,
          "CardName": "Voice of Victory"
        }
      ],
      "Sideboard": [
        {
          "Count": 1,
          "CardName": "Abrade"
        },
        {
          "Count": 1,
          "CardName": "Beza, the Bounding Spring"
        },
        {
          "Count": 1,
          "CardName": "Chandra, Spark Hunter"
        },
        {
          "Count": 2,
          "CardName": "Destroy Evil"
        },
        {
          "Count": 1,
          "CardName": "Elspeth, Storm Slayer"
        },
        {
          "Count": 2,
          "CardName": "Get Lost"
        },
        {
          "Count": 1,
          "CardName": "Loran of the Third Path"
        },
        {
          "Count": 2,
          "CardName": "Rest in Peace"
        },
        {
          "Count": 1,
          "CardName": "Serra Paragon"
        },
        {
          "Count": 1,
          "CardName": "Sword of Once and Future"
        },
        {
          "Count": 2,
          "CardName": "Torch the Tower"
        }
      ]
    }
  ],
  "Rounds": [],
  "Standings": []
}